cli/__init__.py
cli/agent.py
cli/apiexternal.py
cli/collector.py
cli/consts.py
cli/docopt_command.py
cli/file_event_search.py
cli/image.py
cli/inspections.py
cli/integration.py
cli/logger.ini
cli/main.py
cli/reputation.py
cli/util.py
cli/workspace.py
cli/schemas/reputation_schema_v1.json
vp_cli-0.1.12.dist-info/METADATA
vp_cli-0.1.12.dist-info/WHEEL
vp_cli-0.1.12.dist-info/entry_points.txt
vp_cli-0.1.12.dist-info/top_level.txt
vp_cli-0.1.12.dist-info/RECORD
